bombcell/__init__.py
bombcell/ccg_fast.py
bombcell/classification.py
bombcell/default_parameters.py
bombcell/ephys_properties.py
bombcell/extract_raw_waveforms.py
bombcell/gui_sandbox.py
bombcell/helper_functions.py
bombcell/loading_utils.py
bombcell/manual_analysis.py
bombcell/plot_functions.py
bombcell/plotting_utils.py
bombcell/quality_metrics.py
bombcell/save_utils.py
bombcell/unit_quality_gui.py
bombcell-0.72.dist-info/METADATA
bombcell-0.72.dist-info/WHEEL
bombcell-0.72.dist-info/top_level.txt
bombcell-0.72.dist-info/RECORD
