Metadata-Version: 2.4
Name: bombcell
Version: 0.72
Summary: Python port of bombcell. Automated quality control, curation and neuron classification of spike-sorted electrophysiology data.
Author: Julie Fabre, Sam Dodgson, Maxime Beau
Maintainer-email: Julie Fabre <julie.m.fabre@gmail.com>
License: GPL-3.0
Project-URL: Homepage, https://github.com/Julie-Fabre/bombcell
Project-URL: Repository, https://github.com/Julie-Fabre/bombcell
Project-URL: Issues, https://github.com/Julie-Fabre/bombcell/issues
Classifier: Development Status :: 4 - Beta
Classifier: Intended Audience :: Science/Research
Classifier: License :: OSI Approved :: GNU General Public License v3 (GPLv3)
Classifier: Programming Language :: Python :: 3
Classifier: Programming Language :: Python :: 3.8
Classifier: Programming Language :: Python :: 3.9
Classifier: Programming Language :: Python :: 3.10
Classifier: Programming Language :: Python :: 3.11
Classifier: Topic :: Scientific/Engineering :: Bio-Informatics
Requires-Python: >=3.8
Requires-Dist: numpy>=1.19.0
Requires-Dist: scipy>=1.7.0
Requires-Dist: matplotlib>=3.3.0
Requires-Dist: pandas>=1.3.0
Requires-Dist: ipywidgets>=7.6.0
Requires-Dist: joblib>=1.0.0
Requires-Dist: tqdm>=4.50.0
Requires-Dist: pyarrow>=5.0.0
Requires-Dist: numba>=0.58.1
Requires-Dist: upsetplot
Requires-Dist: mtscomp
Requires-Dist: cachecache
